odoo/addons/iap_alternative_provider/README.rst
odoo/addons/iap_alternative_provider/__init__.py
odoo/addons/iap_alternative_provider/__manifest__.py
odoo/addons/iap_alternative_provider/i18n/ca.po
odoo/addons/iap_alternative_provider/i18n/es.po
odoo/addons/iap_alternative_provider/i18n/iap_alternative_provider.pot
odoo/addons/iap_alternative_provider/i18n/it.po
odoo/addons/iap_alternative_provider/i18n/zh_CN.po
odoo/addons/iap_alternative_provider/models/__init__.py
odoo/addons/iap_alternative_provider/models/iap_account.py
odoo/addons/iap_alternative_provider/readme/CONTRIBUTORS.md
odoo/addons/iap_alternative_provider/readme/DESCRIPTION.md
odoo/addons/iap_alternative_provider/static/description/icon.png
odoo/addons/iap_alternative_provider/static/description/index.html
odoo/addons/iap_alternative_provider/tests/__init__.py
odoo/addons/iap_alternative_provider/tests/test_iap_account.py
odoo/addons/iap_alternative_provider/views/iap_account_view.xml
odoo_addon_iap_alternative_provider-18.0.1.0.0.2.dist-info/METADATA
odoo_addon_iap_alternative_provider-18.0.1.0.0.2.dist-info/WHEEL
odoo_addon_iap_alternative_provider-18.0.1.0.0.2.dist-info/top_level.txt
odoo_addon_iap_alternative_provider-18.0.1.0.0.2.dist-info/RECORD
