Metadata-Version: 2.1
Name: odoo-addon-iap_alternative_provider
Version: 18.0.1.0.0.2
Requires-Python: >=3.10
Requires-Dist: odoo==18.0.*
Summary: Base module for providing alternative provider for iap apps
Home-page: https://github.com/OCA/server-tools
License: AGPL-3
Author: Akretion, Odoo Community Association (OCA)
Author-email: support@odoo-community.org
Classifier: Programming Language :: Python
Classifier: Framework :: Odoo
Classifier: Framework :: Odoo :: 18.0
Classifier: License :: OSI Approved :: GNU Affero General Public License v3
